{
  "page": 1,
  "value": [
    {
      "path": "_news/2020-06-29-announcing-general-availability-ga-of-enhanced-connectivity-for-snowflake.md",
      "title": "Announcing General Availability (GA) of enhanced connectivity for Snowflake",
      "excerpt": "We are excited to announce the that the enhanced capabilities added recently to the Power BI Snowflake connector are now GA, including the ability to connect to Snowflake without an on-premises data gateway as well as support for Azure Active Directory (AAD) authentication and SSO in DirectQuery mode",
      "webUrl": "https://powerbi.microsoft.com/en-us/blog/announcing-general-availability-ga-of-enhanced-connectivity-for-snowflake/",
      "heat": 80,
      "tags": null,
      "images": [
        {
          "url": "https://powerbi.microsoft.com/pictures/shared/social/social-default-image.png",
          "width": 418,
          "height": 417,
          "title": "Announcing General Availability (GA) of enhanced connectivity for Snowflake",
          "attribution": null,
          "isCached": true
        }
      ],
      "type": "article",
      "ampWebUrl": null,
      "cdnAmpWebUrl": null,
      "publishedDateTime": "2020-06-29T02:20:23-07:00",
      "updatedDateTime": null,
      "provider": {
        "name": "Microsoft",
        "domain": "microsoft.com",
        "images": [
          {
            "url": "https://smartableai.github.io/microsoft-power-bi/assets/images/organizations/microsoft.com-50x50.jpg",
            "width": 50,
            "height": 50,
            "title": null,
            "attribution": null,
            "isCached": false
          }
        ],
        "publishers": null,
        "authors": null
      },
      "locale": "en-us",
      "categories": [
        "news"
      ],
      "topics": [
        "Power BI"
      ]
    },
    {
      "path": "_news/2020-06-22-what-to-focus-on-with-dax-and-more-roundup-june-22-2020.md",
      "title": "What to FOCUS on with DAX and more... (Roundup | June 22, 2020)",
      "excerpt": "Thanks for watching this week's Power BI news roundup!  Last weeks roundup: https://guyinacu.be/roundup183 2 Minute Tuesday: https://guyinacu.be/datarefresh Adam's tech video: https://guyinacu.be/perfstart  🔴 Live Replay: https://guyinacu.be/live015  📢 Become a member: https://guyinacu.be/membership",
      "webUrl": "https://youtube.com/watch?v=YvSuCayng30",
      "heat": 124,
      "tags": null,
      "images": [
        {
          "url": "https://i.ytimg.com/vi/YvSuCayng30/maxresdefault.jpg",
          "width": 1280,
          "height": 720,
          "title": "What to FOCUS on with DAX and more... (Roundup | June 22, 2020)",
          "attribution": null,
          "isCached": true
        }
      ],
      "type": "video",
      "ampWebUrl": null,
      "cdnAmpWebUrl": null,
      "publishedDateTime": "2020-06-22T08:00:25-07:00",
      "updatedDateTime": null,
      "provider": {
        "name": "Guy in a Cube",
        "domain": "guyinacube.com",
        "images": [
          {
            "url": "https://smartableai.github.io/microsoft-power-bi/assets/images/organizations/guyinacube.com-50x50.jpg",
            "width": 50,
            "height": 50,
            "title": null,
            "attribution": null,
            "isCached": false
          }
        ],
        "publishers": null,
        "authors": null
      },
      "locale": "en-us",
      "categories": [
        "news"
      ],
      "topics": [
        "Power BI"
      ]
    },
    {
      "path": "_news/2020-06-18-power-bi-desktop-update-june-2020.md",
      "title": "Power BI Desktop Update - June 2020",
      "excerpt": "We have great updates this release! We're super excited to announce this month that several features are now generally available: automatic page refresh, the hierarchy slicer, the modern ribbon, and AI insights are now generally available. On top of this, we have several new features and updates that",
      "webUrl": "https://youtube.com/watch?v=WUo8TnHNHYM",
      "heat": 154,
      "tags": null,
      "images": [
        {
          "url": "https://i.ytimg.com/vi/WUo8TnHNHYM/maxresdefault.jpg",
          "width": 1280,
          "height": 720,
          "title": "Power BI Desktop Update - June 2020",
          "attribution": null,
          "isCached": true
        }
      ],
      "type": "video",
      "ampWebUrl": null,
      "cdnAmpWebUrl": null,
      "publishedDateTime": "2020-06-18T10:24:47-07:00",
      "updatedDateTime": null,
      "provider": {
        "name": "Microsoft",
        "domain": "microsoft.com",
        "images": [
          {
            "url": "https://smartableai.github.io/microsoft-power-bi/assets/images/organizations/microsoft.com-50x50.jpg",
            "width": 50,
            "height": 50,
            "title": null,
            "attribution": null,
            "isCached": false
          }
        ],
        "publishers": null,
        "authors": null
      },
      "locale": "en-us",
      "categories": [
        "news"
      ],
      "topics": [
        "Power BI",
        "Power BI Desktop"
      ]
    },
    {
      "path": "_news/2020-06-17-get-the-2020-master-microsoft-excel-power-bi-certification-bundle-for-just-3499.md",
      "title": "Get the 2020 Master Microsoft Excel & Power BI Certification Bundle for just $34.99",
      "excerpt": "Become the data-driven hero companies need with 28 hours of training in data plotting, auto calculation, macros, visualization and more with today's highlighted deal. Get it via Neowin Deals!",
      "webUrl": "https://www.neowin.net/news/get-the-2020-master-microsoft-excel--power-bi-certification-bundle-for-just-3499",
      "heat": 91,
      "tags": null,
      "images": [
        {
          "url": "https://cdn.neow.in/news/images/uploaded/2020/06/1592381669_product_38938_product_shot_wide_story.jpg",
          "width": 760,
          "height": 380,
          "title": "Get the 2020 Master Microsoft Excel & Power BI Certification Bundle for just $34.99",
          "attribution": null,
          "isCached": true
        }
      ],
      "type": "article",
      "ampWebUrl": "https://www.neowin.net/amp/get-the-2020-master-microsoft-excel--power-bi-certification-bundle-for-just-3499/",
      "cdnAmpWebUrl": "https://www-neowin-net.cdn.ampproject.org/c/s/www.neowin.net/amp/get-the-2020-master-microsoft-excel--power-bi-certification-bundle-for-just-3499/",
      "publishedDateTime": "2020-06-17T09:46:00-07:00",
      "updatedDateTime": null,
      "provider": {
        "name": "Neowin",
        "domain": "neowin.net",
        "images": [
          {
            "url": "https://smartableai.github.io/microsoft-power-bi/assets/images/organizations/neowin.net-50x50.jpg",
            "width": 50,
            "height": 50,
            "title": null,
            "attribution": null,
            "isCached": false
          }
        ],
        "publishers": null,
        "authors": null
      },
      "locale": "en-us",
      "categories": [
        "news"
      ],
      "topics": [
        "Power BI"
      ]
    },
    {
      "path": "_news/2020-06-17-new-way-of-getting-apps.md",
      "title": "New way of getting apps",
      "excerpt": "We’re thrilled to introduce a new look for getting apps! As of today, getting an app from your organization or from the AppSource marketplace has never been easier!",
      "webUrl": "https://powerbi.microsoft.com/en-us/blog/new-way-of-getting-apps/",
      "heat": 82,
      "tags": null,
      "images": [
        {
          "url": "https://powerbi.microsoft.com/pictures/shared/social/social-default-image.png",
          "width": 418,
          "height": 417,
          "title": "New way of getting apps",
          "attribution": null,
          "isCached": true
        }
      ],
      "type": "article",
      "ampWebUrl": null,
      "cdnAmpWebUrl": null,
      "publishedDateTime": "2020-06-17T03:37:33-07:00",
      "updatedDateTime": null,
      "provider": {
        "name": "Microsoft",
        "domain": "microsoft.com",
        "images": [
          {
            "url": "https://smartableai.github.io/microsoft-power-bi/assets/images/organizations/microsoft.com-50x50.jpg",
            "width": 50,
            "height": 50,
            "title": null,
            "attribution": null,
            "isCached": false
          }
        ],
        "publishers": null,
        "authors": null
      },
      "locale": "en-us",
      "categories": [
        "news"
      ],
      "topics": [
        "Power BI"
      ]
    },
    {
      "path": "_news/2020-06-16-licensing-and-roadmap-update-for-power-bi-report-server.md",
      "title": "Licensing and roadmap update for Power BI Report Server",
      "excerpt": "Since Power BI Report Server launched in June 2017, it’s been adopted by thousands of customers in a variety of industries, giving them a way to use and share Power BI reports on-premises.",
      "webUrl": "https://powerbi.microsoft.com/en-us/blog/licensing-and-roadmap-update-for-power-bi-report-server/",
      "heat": 97,
      "tags": null,
      "images": [
        {
          "url": "https://powerbi.microsoft.com/pictures/shared/social/social-default-image.png",
          "width": 418,
          "height": 417,
          "title": "Licensing and roadmap update for Power BI Report Server",
          "attribution": null,
          "isCached": true
        }
      ],
      "type": "article",
      "ampWebUrl": null,
      "cdnAmpWebUrl": null,
      "publishedDateTime": "2020-06-16T02:46:02-07:00",
      "updatedDateTime": null,
      "provider": {
        "name": "Microsoft",
        "domain": "microsoft.com",
        "images": [
          {
            "url": "https://smartableai.github.io/microsoft-power-bi/assets/images/organizations/microsoft.com-50x50.jpg",
            "width": 50,
            "height": 50,
            "title": null,
            "attribution": null,
            "isCached": false
          }
        ],
        "publishers": null,
        "authors": null
      },
      "locale": "en-us",
      "categories": [
        "news"
      ],
      "topics": [
        "Power BI"
      ]
    },
    {
      "path": "_news/2020-06-15-power-bi-updates-dax-fusion-and-data-driven-subscriptions-roundup-june-15-2020.md",
      "title": "Power BI updates, DAX Fusion, and data driven subscriptions (Roundup | June 15, 2020)",
      "excerpt": "Thanks for watching this week's Power BI news roundup!  Last weeks roundup: https://guyinacu.be/roundup182 2 Minute Tuesday: https://guyinacu.be/askquestions Patrick's tech video: https://guyinacu.be/blankslicer Adam's tech video: https://guyinacu.be/workspaceroadmap  🔴 Live Replay with Marco Russo:",
      "webUrl": "https://youtube.com/watch?v=-7Wk8FPz7es",
      "heat": 131,
      "tags": null,
      "images": [
        {
          "url": "https://i.ytimg.com/vi/-7Wk8FPz7es/maxresdefault.jpg",
          "width": 1280,
          "height": 720,
          "title": "Power BI updates, DAX Fusion, and data driven subscriptions (Roundup | June 15, 2020)",
          "attribution": null,
          "isCached": true
        }
      ],
      "type": "video",
      "ampWebUrl": null,
      "cdnAmpWebUrl": null,
      "publishedDateTime": "2020-06-15T08:00:02-07:00",
      "updatedDateTime": null,
      "provider": {
        "name": "Guy in a Cube",
        "domain": "guyinacube.com",
        "images": [
          {
            "url": "https://smartableai.github.io/microsoft-power-bi/assets/images/organizations/guyinacube.com-50x50.jpg",
            "width": 50,
            "height": 50,
            "title": null,
            "attribution": null,
            "isCached": false
          }
        ],
        "publishers": null,
        "authors": null
      },
      "locale": "en-us",
      "categories": [
        "news"
      ],
      "topics": [
        "Power BI"
      ]
    },
    {
      "path": "_news/2020-06-11-on-premises-data-gateway-june-2020-update-is-now-available.md",
      "title": "On-premises data gateway June 2020 update is now available",
      "excerpt": "June release of gateway",
      "webUrl": "https://powerbi.microsoft.com/en-us/blog/on-premises-data-gateway-june-2020-update-is-now-available/",
      "heat": 82,
      "tags": null,
      "images": [
        {
          "url": "https://powerbi.microsoft.com/pictures/shared/social/social-default-image.png",
          "width": 418,
          "height": 417,
          "title": "On-premises data gateway June 2020 update is now available",
          "attribution": null,
          "isCached": true
        }
      ],
      "type": "article",
      "ampWebUrl": null,
      "cdnAmpWebUrl": null,
      "publishedDateTime": "2020-06-11T03:19:15-07:00",
      "updatedDateTime": null,
      "provider": {
        "name": "Microsoft",
        "domain": "microsoft.com",
        "images": [
          {
            "url": "https://smartableai.github.io/microsoft-power-bi/assets/images/organizations/microsoft.com-50x50.jpg",
            "width": 50,
            "height": 50,
            "title": null,
            "attribution": null,
            "isCached": false
          }
        ],
        "publishers": null,
        "authors": null
      },
      "locale": "en-us",
      "categories": [
        "news"
      ],
      "topics": [
        "Power BI"
      ]
    },
    {
      "path": "_news/2020-06-11-announcing-power-bi-data-protection-ga-and-introducing-new-capabilities.md",
      "title": "Announcing Power BI data protection GA and introducing new capabilities",
      "excerpt": "Last fall we introduced industry-leading Power BI data protection capabilities in public preview. Today we’re happy to announce these capabilities are generally available (GA), along with new and exciting capabilities we’re announcing in this space!\r\nPower BI helps organizations empower everyone to make",
      "webUrl": "https://powerbi.microsoft.com/en-us/blog/announcing-power-bi-data-protection-ga-and-introducing-new-capabilities/",
      "heat": 97,
      "tags": null,
      "images": [
        {
          "url": "https://powerbi.microsoft.com/pictures/shared/social/social-default-image.png",
          "width": 418,
          "height": 417,
          "title": "Announcing Power BI data protection GA and introducing new capabilities",
          "attribution": null,
          "isCached": true
        }
      ],
      "type": "article",
      "ampWebUrl": null,
      "cdnAmpWebUrl": null,
      "publishedDateTime": "2020-06-11T02:10:00-07:00",
      "updatedDateTime": null,
      "provider": {
        "name": "Microsoft",
        "domain": "microsoft.com",
        "images": [
          {
            "url": "https://smartableai.github.io/microsoft-power-bi/assets/images/organizations/microsoft.com-50x50.jpg",
            "width": 50,
            "height": 50,
            "title": null,
            "attribution": null,
            "isCached": false
          }
        ],
        "publishers": null,
        "authors": null
      },
      "locale": "en-us",
      "categories": [
        "news"
      ],
      "topics": [
        "Power BI"
      ]
    },
    {
      "path": "_news/2020-06-10-the-theme-youve-been-waiting-for-dark-mode-comes-to-the-power-bi-ios-app.md",
      "title": "The theme you᾿ve been waiting for – Dark mode comes to the Power BI iOS app",
      "excerpt": "In this week’s release we’ve added dark mode support to the Power BI iOS app. Power BI Mobile users know that we’re always working to improve our apps and looking for ways to provide our users the best, most delightful, and enjoyable experience possible. And enabling dark mode is one of those things",
      "webUrl": "https://powerbi.microsoft.com/en-us/blog/the-theme-youve-been-waiting-for-dark-mode-comes-to-the-power-bi-ios-app/",
      "heat": 95,
      "tags": null,
      "images": [
        {
          "url": "https://powerbi.microsoft.com/pictures/shared/social/social-default-image.png",
          "width": 418,
          "height": 417,
          "title": "The theme you᾿ve been waiting for – Dark mode comes to the Power BI iOS app",
          "attribution": null,
          "isCached": true
        }
      ],
      "type": "article",
      "ampWebUrl": null,
      "cdnAmpWebUrl": null,
      "publishedDateTime": "2020-06-10T16:53:10-07:00",
      "updatedDateTime": null,
      "provider": {
        "name": "Microsoft",
        "domain": "microsoft.com",
        "images": [
          {
            "url": "https://smartableai.github.io/microsoft-power-bi/assets/images/organizations/microsoft.com-50x50.jpg",
            "width": 50,
            "height": 50,
            "title": null,
            "attribution": null,
            "isCached": false
          }
        ],
        "publishers": null,
        "authors": null
      },
      "locale": "en-us",
      "categories": [
        "news"
      ],
      "topics": [
        "Power BI"
      ]
    },
    {
      "path": "_news/2020-06-10-power-bi-for-ios-gets-updated-with-dark-mode-support.md",
      "title": "Power BI for iOS gets updated with dark mode support",
      "excerpt": "The Power BI app for iOS has received a new update. The latest update adds support for dark mode to the app. Earlier, Microsoft noted that it will add dark mode to Power BI mobile apps in June 2020.",
      "webUrl": "https://www.neowin.net/news/power-bi-for-ios-gets-updated-with-dark-mode-support",
      "heat": 98,
      "tags": null,
      "images": [
        {
          "url": "https://cdn.neow.in/news/images/uploaded/2019/11/1574779301_powerbi1_story.jpg",
          "width": 760,
          "height": 428,
          "title": "Power BI for iOS gets updated with dark mode support",
          "attribution": null,
          "isCached": true
        }
      ],
      "type": "article",
      "ampWebUrl": "https://www.neowin.net/amp/power-bi-for-ios-gets-updated-with-dark-mode-support/",
      "cdnAmpWebUrl": "https://www-neowin-net.cdn.ampproject.org/c/s/www.neowin.net/amp/power-bi-for-ios-gets-updated-with-dark-mode-support/",
      "publishedDateTime": "2020-06-10T06:22:00-07:00",
      "updatedDateTime": null,
      "provider": {
        "name": "Neowin",
        "domain": "neowin.net",
        "images": [
          {
            "url": "https://smartableai.github.io/microsoft-power-bi/assets/images/organizations/neowin.net-50x50.jpg",
            "width": 50,
            "height": 50,
            "title": null,
            "attribution": null,
            "isCached": false
          }
        ],
        "publishers": null,
        "authors": null
      },
      "locale": "en-us",
      "categories": [
        "news"
      ],
      "topics": [
        "Power BI"
      ]
    },
    {
      "path": "_news/2020-06-10-power-bi-desktop-june-2020-feature-summary.md",
      "title": "Power BI Desktop June 2020 Feature Summary",
      "excerpt": "We have great updates this release! We&#8217;re super excited to announce this month that several features are now generally available: automatic page refresh, the hierarchy slicer, the modern ribbon, and AI insights are now generally available. On top of this, we have several new features and updates",
      "webUrl": "https://powerbi.microsoft.com/en-us/blog/power-bi-desktop-june-2020-feature-summary/",
      "heat": 97,
      "tags": null,
      "images": [
        {
          "url": "https://powerbi.microsoft.com/pictures/shared/social/social-default-image.png",
          "width": 418,
          "height": 417,
          "title": "Power BI Desktop June 2020 Feature Summary",
          "attribution": null,
          "isCached": true
        }
      ],
      "type": "article",
      "ampWebUrl": null,
      "cdnAmpWebUrl": null,
      "publishedDateTime": "2020-06-10T06:12:15-07:00",
      "updatedDateTime": null,
      "provider": {
        "name": "Microsoft",
        "domain": "microsoft.com",
        "images": [
          {
            "url": "https://smartableai.github.io/microsoft-power-bi/assets/images/organizations/microsoft.com-50x50.jpg",
            "width": 50,
            "height": 50,
            "title": null,
            "attribution": null,
            "isCached": false
          }
        ],
        "publishers": null,
        "authors": null
      },
      "locale": "en-us",
      "categories": [
        "news"
      ],
      "topics": [
        "Power BI"
      ]
    },
    {
      "path": "_news/2020-06-10-create-stunning-mobile-reports-with-the-updated-mobile-authoring-in-power-bi-desktop.md",
      "title": "Create stunning mobile reports with the updated mobile authoring in Power BI Desktop",
      "excerpt": "We are exciting to introduce an improved mobile layout authoring experience. With the new capabilities introduced in this release, you can build compelling, interactive reports optimized for mobile devices.",
      "webUrl": "https://powerbi.microsoft.com/en-us/blog/create-stunning-mobile-reports-with-the-updated-mobile-authoring-in-power-bi-desktop/",
      "heat": 90,
      "tags": null,
      "images": [
        {
          "url": "https://powerbi.microsoft.com/pictures/shared/social/social-default-image.png",
          "width": 418,
          "height": 417,
          "title": "Create stunning mobile reports with the updated mobile authoring in Power BI Desktop",
          "attribution": null,
          "isCached": true
        }
      ],
      "type": "article",
      "ampWebUrl": null,
      "cdnAmpWebUrl": null,
      "publishedDateTime": "2020-06-10T06:08:40-07:00",
      "updatedDateTime": null,
      "provider": {
        "name": "Microsoft",
        "domain": "microsoft.com",
        "images": [
          {
            "url": "https://smartableai.github.io/microsoft-power-bi/assets/images/organizations/microsoft.com-50x50.jpg",
            "width": 50,
            "height": 50,
            "title": null,
            "attribution": null,
            "isCached": false
          }
        ],
        "publishers": null,
        "authors": null
      },
      "locale": "en-us",
      "categories": [
        "news"
      ],
      "topics": [
        "Power BI"
      ]
    },
    {
      "path": "_news/2020-06-08-learn-todays-top-data-analysis-tools-microsoft-excel-and-power-bi-with-this-35-bundle.md",
      "title": "Learn Today's Top Data Analysis Tools, Microsoft Excel, and Power BI with This $35 Bundle",
      "excerpt": "The 2020 Master Microsoft Excel & Power BI Certification Bundle will teach you what you need to know. This nine-course bundle will get you up to speed on some of today's top data analysis tools ...",
      "webUrl": "https://www.entrepreneur.com/article/351506",
      "heat": 88,
      "tags": null,
      "images": [
        {
          "url": "https://assets.entrepreneur.com/content/3x2/2000/1591317005-Ent-PowerBIandExcel.jpg?width=600&crop=16:9",
          "width": 600,
          "height": 338,
          "title": "Learn Today's Top Data Analysis Tools, Microsoft Excel, and Power BI with This $35 Bundle",
          "attribution": null,
          "isCached": true
        }
      ],
      "type": "article",
      "ampWebUrl": "https://www.entrepreneur.com/amphtml/351506",
      "cdnAmpWebUrl": "https://www-entrepreneur-com.cdn.ampproject.org/c/s/www.entrepreneur.com/amphtml/351506",
      "publishedDateTime": "2020-06-08T09:55:00-07:00",
      "updatedDateTime": null,
      "provider": {
        "name": "Entrepreneur",
        "domain": "entrepreneur.com",
        "images": [
          {
            "url": "https://smartableai.github.io/microsoft-power-bi/assets/images/organizations/entrepreneur.com-50x50.jpg",
            "width": 50,
            "height": 50,
            "title": null,
            "attribution": null,
            "isCached": false
          }
        ],
        "publishers": null,
        "authors": null
      },
      "locale": "en-us",
      "categories": [
        "news"
      ],
      "topics": [
        "Power BI"
      ]
    },
    {
      "path": "_news/2020-06-08-power-bi-quizzes-data-masking-and-more-roundup-june-8-2020.md",
      "title": "Power BI quizzes, data masking and more... (Roundup | June 8, 2020)",
      "excerpt": "Thanks for watching this week's Power BI news roundup!  Last weeks roundup: https://guyinacu.be/roundup181 2 Minute Tuesday: https://guyinacu.be/dataflowstricks Patrick's tech video: https://guyinacu.be/synapse Adam's tech video: https://guyinacu.be/pipelines  🔴 Live replay: https://guyinacu.be/live013",
      "webUrl": "https://youtube.com/watch?v=876kLN_vBJE",
      "heat": 137,
      "tags": null,
      "images": [
        {
          "url": "https://i.ytimg.com/vi/876kLN_vBJE/maxresdefault.jpg",
          "width": 1280,
          "height": 720,
          "title": "Power BI quizzes, data masking and more... (Roundup | June 8, 2020)",
          "attribution": null,
          "isCached": true
        }
      ],
      "type": "video",
      "ampWebUrl": null,
      "cdnAmpWebUrl": null,
      "publishedDateTime": "2020-06-08T08:00:10-07:00",
      "updatedDateTime": null,
      "provider": {
        "name": "Guy in a Cube",
        "domain": "guyinacube.com",
        "images": [
          {
            "url": "https://smartableai.github.io/microsoft-power-bi/assets/images/organizations/guyinacube.com-50x50.jpg",
            "width": 50,
            "height": 50,
            "title": null,
            "attribution": null,
            "isCached": false
          }
        ],
        "publishers": null,
        "authors": null
      },
      "locale": "en-us",
      "categories": [
        "news"
      ],
      "topics": [
        "Power BI"
      ]
    },
    {
      "path": "_news/2020-06-01-power-bi-workspace-roadmap-directquery-dataflows-and-more-roundup-june-1-2020.md",
      "title": "Power BI Workspace Roadmap, DirectQuery dataflows and more... (Roundup | June 1, 2020)",
      "excerpt": "Thanks for watching this week's Power BI news roundup!  Last roundup: https://guyinacu.be/roundup180 2 Minute Tuesday: https://guyinacu.be/animatedvisuals  🔴 Live Stream Replay: https://guyinacu.be/live012  📢 Become a member: https://guyinacu.be/membership   *******************  Want to take your Power",
      "webUrl": "https://youtube.com/watch?v=f1XqbeOSWyg",
      "heat": 129,
      "tags": null,
      "images": [
        {
          "url": "https://i.ytimg.com/vi/f1XqbeOSWyg/maxresdefault.jpg",
          "width": 1280,
          "height": 720,
          "title": "Power BI Workspace Roadmap, DirectQuery dataflows and more... (Roundup | June 1, 2020)",
          "attribution": null,
          "isCached": true
        }
      ],
      "type": "video",
      "ampWebUrl": null,
      "cdnAmpWebUrl": null,
      "publishedDateTime": "2020-06-01T08:00:23-07:00",
      "updatedDateTime": null,
      "provider": {
        "name": "Guy in a Cube",
        "domain": "guyinacube.com",
        "images": [
          {
            "url": "https://smartableai.github.io/microsoft-power-bi/assets/images/organizations/guyinacube.com-50x50.jpg",
            "width": 50,
            "height": 50,
            "title": null,
            "attribution": null,
            "isCached": false
          }
        ],
        "publishers": null,
        "authors": null
      },
      "locale": "en-us",
      "categories": [
        "news"
      ],
      "topics": [
        "Power BI"
      ]
    },
    {
      "path": "_news/2020-05-29-roadmap-update-whats-next-for-the-new-workspace-experience-upgrade-in-the-coming-months.md",
      "title": "Roadmap update: What᾿s next for the new workspace experience upgrade in the coming months",
      "excerpt": "Today, we wanted to announce our roadmap for workspace upgrade so you can plan ahead.  We also announce in this post our classic workspace deprecation plans. If you&#8217;re a Power BI admin or workspace admin, this is a must read. ",
      "webUrl": "https://powerbi.microsoft.com/en-us/blog/roadmap-update-whats-next-for-the-new-workspace-experience-upgrade-in-the-coming-months/",
      "heat": 73,
      "tags": null,
      "images": [
        {
          "url": "https://powerbiblogscdn.azureedge.net/wp-content/uploads/2020/05/workspace-upgrade-block-classic-create.png",
          "width": 1197,
          "height": 515,
          "title": "Roadmap update: What᾿s next for the new workspace experience upgrade in the coming months",
          "attribution": null,
          "isCached": true
        }
      ],
      "type": "article",
      "ampWebUrl": null,
      "cdnAmpWebUrl": null,
      "publishedDateTime": "2020-05-29T00:00:15-07:00",
      "updatedDateTime": null,
      "provider": {
        "name": "Microsoft",
        "domain": "microsoft.com",
        "images": [
          {
            "url": "https://smartableai.github.io/microsoft-power-bi/assets/images/organizations/microsoft.com-50x50.jpg",
            "width": 50,
            "height": 50,
            "title": null,
            "attribution": null,
            "isCached": false
          }
        ],
        "publishers": null,
        "authors": null
      },
      "locale": "en-us",
      "categories": [
        "news"
      ],
      "topics": [
        "Power BI"
      ]
    },
    {
      "path": "_news/2020-05-28-power-bi-dataflows-direct-query-support.md",
      "title": "Power BI Dataflows Direct Query Support",
      "excerpt": "We are excited to announce Direct Query support (Preview) for Power BI dataflows.  You can now connect directly to a dataflow without first requiring to import the data into a dataset. ",
      "webUrl": "https://powerbi.microsoft.com/en-us/blog/power-bi-dataflows-direct-query-support/",
      "heat": 97,
      "tags": null,
      "images": [
        {
          "url": "https://powerbi.microsoft.com/pictures/shared/social/social-default-image.png",
          "width": 418,
          "height": 417,
          "title": "Power BI Dataflows Direct Query Support",
          "attribution": null,
          "isCached": true
        }
      ],
      "type": "article",
      "ampWebUrl": null,
      "cdnAmpWebUrl": null,
      "publishedDateTime": "2020-05-28T00:00:00-07:00",
      "updatedDateTime": null,
      "provider": {
        "name": "Microsoft",
        "domain": "microsoft.com",
        "images": [
          {
            "url": "https://smartableai.github.io/microsoft-power-bi/assets/images/organizations/microsoft.com-50x50.jpg",
            "width": 50,
            "height": 50,
            "title": null,
            "attribution": null,
            "isCached": false
          }
        ],
        "publishers": null,
        "authors": null
      },
      "locale": "en-us",
      "categories": [
        "news"
      ],
      "topics": [
        "Power BI"
      ]
    },
    {
      "path": "_news/2020-05-28-power-bi-report-server-may-2020-feature-summary.md",
      "title": "Power BI Report Server May 2020 Feature Summary",
      "excerpt": "We are excited to bring you a new version of Power BI Report Server this month! With this update, we’re releasing a bevy of features across all aspects of Power BI: hierarchical slicer and decomposition tree visuals, query diagnostics, and more. Read on to get the full details of all the new additions!",
      "webUrl": "https://powerbi.microsoft.com/en-us/blog/power-bi-report-server-may-2020-feature-summary/",
      "heat": 97,
      "tags": null,
      "images": [
        {
          "url": "https://powerbi.microsoft.com/pictures/shared/social/social-default-image.png",
          "width": 418,
          "height": 417,
          "title": "Power BI Report Server May 2020 Feature Summary",
          "attribution": null,
          "isCached": true
        }
      ],
      "type": "article",
      "ampWebUrl": null,
      "cdnAmpWebUrl": null,
      "publishedDateTime": "2020-05-27T23:00:00-07:00",
      "updatedDateTime": null,
      "provider": {
        "name": "Microsoft",
        "domain": "microsoft.com",
        "images": [
          {
            "url": "https://smartableai.github.io/microsoft-power-bi/assets/images/organizations/microsoft.com-50x50.jpg",
            "width": 50,
            "height": 50,
            "title": null,
            "attribution": null,
            "isCached": false
          }
        ],
        "publishers": null,
        "authors": null
      },
      "locale": "en-us",
      "categories": [
        "news"
      ],
      "topics": [
        "Power BI"
      ]
    },
    {
      "path": "_news/2020-05-26-page-view-for-paginated-reports-now-available-in-power-bi.md",
      "title": "Page view for Paginated Reports now available in Power BI",
      "excerpt": "We are pleased to announce the new page view option for Paginated Reports is now available in the Power BI service.",
      "webUrl": "https://powerbi.microsoft.com/en-us/blog/page-view-for-paginated-reports-now-available-in-power-bi/",
      "heat": 97,
      "tags": null,
      "images": [
        {
          "url": "https://powerbi.microsoft.com/pictures/shared/social/social-default-image.png",
          "width": 418,
          "height": 417,
          "title": "Page view for Paginated Reports now available in Power BI",
          "attribution": null,
          "isCached": true
        }
      ],
      "type": "article",
      "ampWebUrl": null,
      "cdnAmpWebUrl": null,
      "publishedDateTime": "2020-05-26T04:49:57-07:00",
      "updatedDateTime": null,
      "provider": {
        "name": "Microsoft",
        "domain": "microsoft.com",
        "images": [
          {
            "url": "https://smartableai.github.io/microsoft-power-bi/assets/images/organizations/microsoft.com-50x50.jpg",
            "width": 50,
            "height": 50,
            "title": null,
            "attribution": null,
            "isCached": false
          }
        ],
        "publishers": null,
        "authors": null
      },
      "locale": "en-us",
      "categories": [
        "news"
      ],
      "topics": [
        "Power BI"
      ]
    },
    {
      "path": "_news/2020-05-22-power-bi-desktop-update-may-2020.md",
      "title": "Power BI Desktop Update - May 2020",
      "excerpt": "We have lots of great updates this release! We’re super excited to announce this month that both the decomposition tree and drill through button actions are now generally available. On top of this, we have several new features and updates that will really enrich your reporting: curate featured tables",
      "webUrl": "https://youtube.com/watch?v=JtuHIslowxk",
      "heat": 154,
      "tags": null,
      "images": [
        {
          "url": "https://i.ytimg.com/vi/JtuHIslowxk/maxresdefault.jpg",
          "width": 1280,
          "height": 720,
          "title": "Power BI Desktop Update - May 2020",
          "attribution": null,
          "isCached": true
        }
      ],
      "type": "video",
      "ampWebUrl": null,
      "cdnAmpWebUrl": null,
      "publishedDateTime": "2020-05-22T12:24:56-07:00",
      "updatedDateTime": null,
      "provider": {
        "name": "Microsoft",
        "domain": "microsoft.com",
        "images": [
          {
            "url": "https://smartableai.github.io/microsoft-power-bi/assets/images/organizations/microsoft.com-50x50.jpg",
            "width": 50,
            "height": 50,
            "title": null,
            "attribution": null,
            "isCached": false
          }
        ],
        "publishers": null,
        "authors": null
      },
      "locale": "en-us",
      "categories": [
        "news"
      ],
      "topics": [
        "Power BI",
        "Power BI Desktop"
      ]
    },
    {
      "path": "_news/2020-05-21-microsoft-business-applications-summit-2020-power-platform-sessions-quick-reference.md",
      "title": "Microsoft Business Applications Summit 2020 – Power Platform sessions quick reference",
      "excerpt": "You asked for the sessions, and we&#8217;ve got them for you! View over 50 great sessions from the Microsoft Business Applications Summit 2020. Here&#8217;s the Power Platform sessions quick reference blog",
      "webUrl": "https://powerbi.microsoft.com/en-us/blog/microsoft-business-applications-summit-2020-power-platform-sessions-quick-reference/",
      "heat": 75,
      "tags": null,
      "images": [
        {
          "url": "https://powerbi.microsoft.com/pictures/shared/social/social-default-image.png",
          "width": 418,
          "height": 417,
          "title": "Microsoft Business Applications Summit 2020 – Power Platform sessions quick reference",
          "attribution": null,
          "isCached": true
        }
      ],
      "type": "article",
      "ampWebUrl": null,
      "cdnAmpWebUrl": null,
      "publishedDateTime": "2020-05-21T05:49:59-07:00",
      "updatedDateTime": null,
      "provider": {
        "name": "Microsoft",
        "domain": "microsoft.com",
        "images": [
          {
            "url": "https://smartableai.github.io/microsoft-power-bi/assets/images/organizations/microsoft.com-50x50.jpg",
            "width": 50,
            "height": 50,
            "title": null,
            "attribution": null,
            "isCached": false
          }
        ],
        "publishers": null,
        "authors": null
      },
      "locale": "en-us",
      "categories": [
        "news"
      ],
      "topics": [
        "Power BI"
      ]
    },
    {
      "path": "_news/2020-05-21-announcing-general-availability-ga-of-shared-and-certified-datasets-in-power-bi.md",
      "title": "Announcing General Availability (GA) of shared and certified datasets in Power BI",
      "excerpt": "We are excited to announced general availability (GA) of shared and certified datasets in Power BI.",
      "webUrl": "https://powerbi.microsoft.com/en-us/blog/announcing-general-availability-ga-of-shared-and-certified-datasets-in-power-bi/",
      "heat": 92,
      "tags": null,
      "images": [
        {
          "url": "https://powerbi.microsoft.com/pictures/shared/social/social-default-image.png",
          "width": 418,
          "height": 417,
          "title": "Announcing General Availability (GA) of shared and certified datasets in Power BI",
          "attribution": null,
          "isCached": true
        }
      ],
      "type": "article",
      "ampWebUrl": null,
      "cdnAmpWebUrl": null,
      "publishedDateTime": "2020-05-21T03:12:33-07:00",
      "updatedDateTime": null,
      "provider": {
        "name": "Microsoft",
        "domain": "microsoft.com",
        "images": [
          {
            "url": "https://smartableai.github.io/microsoft-power-bi/assets/images/organizations/microsoft.com-50x50.jpg",
            "width": 50,
            "height": 50,
            "title": null,
            "attribution": null,
            "isCached": false
          }
        ],
        "publishers": null,
        "authors": null
      },
      "locale": "en-us",
      "categories": [
        "news"
      ],
      "topics": [
        "Power BI"
      ]
    },
    {
      "path": "_news/2020-05-21-announcing-azure-synapse-analytics-public-preview.md",
      "title": "Announcing Azure Synapse Analytics public preview",
      "excerpt": "Earlier this week, Microsoft announced that Azure Synapse Analytics, the next generation of Azure SQL Data warehouse, is now available for public preview. Azure Synapse provides incredible performance over large data volumes and has built-in capabilities for data ingestion, data preparation, machine",
      "webUrl": "https://powerbi.microsoft.com/en-us/blog/announcing-azure-synapse-analytics-public-preview/",
      "heat": 82,
      "tags": null,
      "images": [
        {
          "url": "https://powerbi.microsoft.com/pictures/shared/social/social-default-image.png",
          "width": 418,
          "height": 417,
          "title": "Announcing Azure Synapse Analytics public preview",
          "attribution": null,
          "isCached": true
        }
      ],
      "type": "article",
      "ampWebUrl": null,
      "cdnAmpWebUrl": null,
      "publishedDateTime": "2020-05-21T01:35:28-07:00",
      "updatedDateTime": null,
      "provider": {
        "name": "Microsoft",
        "domain": "microsoft.com",
        "images": [
          {
            "url": "https://smartableai.github.io/microsoft-power-bi/assets/images/organizations/microsoft.com-50x50.jpg",
            "width": 50,
            "height": 50,
            "title": null,
            "attribution": null,
            "isCached": false
          }
        ],
        "publishers": null,
        "authors": null
      },
      "locale": "en-us",
      "categories": [
        "news"
      ],
      "topics": [
        "Power BI"
      ]
    },
    {
      "path": "_news/2020-05-20-on-premises-data-gateway-may-2020-update-is-now-available.md",
      "title": "On-premises data gateway May 2020 update is now available",
      "excerpt": "May release of gateway",
      "webUrl": "https://powerbi.microsoft.com/en-us/blog/on-premises-data-gateway-may-2020-update-is-now-available/",
      "heat": 82,
      "tags": null,
      "images": [
        {
          "url": "https://powerbi.microsoft.com/pictures/shared/social/social-default-image.png",
          "width": 418,
          "height": 417,
          "title": "On-premises data gateway May 2020 update is now available",
          "attribution": null,
          "isCached": true
        }
      ],
      "type": "article",
      "ampWebUrl": null,
      "cdnAmpWebUrl": null,
      "publishedDateTime": "2020-05-20T01:12:37-07:00",
      "updatedDateTime": null,
      "provider": {
        "name": "Microsoft",
        "domain": "microsoft.com",
        "images": [
          {
            "url": "https://smartableai.github.io/microsoft-power-bi/assets/images/organizations/microsoft.com-50x50.jpg",
            "width": 50,
            "height": 50,
            "title": null,
            "attribution": null,
            "isCached": false
          }
        ],
        "publishers": null,
        "authors": null
      },
      "locale": "en-us",
      "categories": [
        "news"
      ],
      "topics": [
        "Power BI"
      ]
    },
    {
      "path": "_news/2020-05-19-announcing-refresh-summary-for-premium-capacity-admins.md",
      "title": "Announcing Refresh Summary for Premium Capacity Admins",
      "excerpt": "Refresh Summaries Announcement",
      "webUrl": "https://powerbi.microsoft.com/en-us/blog/announcing-refresh-summary-for-premium-capacity-admins/",
      "heat": 82,
      "tags": null,
      "images": [
        {
          "url": "https://powerbi.microsoft.com/pictures/shared/social/social-default-image.png",
          "width": 418,
          "height": 417,
          "title": "Announcing Refresh Summary for Premium Capacity Admins",
          "attribution": null,
          "isCached": true
        }
      ],
      "type": "article",
      "ampWebUrl": null,
      "cdnAmpWebUrl": null,
      "publishedDateTime": "2020-05-19T11:37:40-07:00",
      "updatedDateTime": null,
      "provider": {
        "name": "Microsoft",
        "domain": "microsoft.com",
        "images": [
          {
            "url": "https://smartableai.github.io/microsoft-power-bi/assets/images/organizations/microsoft.com-50x50.jpg",
            "width": 50,
            "height": 50,
            "title": null,
            "attribution": null,
            "isCached": false
          }
        ],
        "publishers": null,
        "authors": null
      },
      "locale": "en-us",
      "categories": [
        "news"
      ],
      "topics": [
        "Power BI"
      ]
    },
    {
      "path": "_news/2020-05-19-power-bi-desktop-may-2020-feature-summary.md",
      "title": "Power BI Desktop May 2020 Feature Summary",
      "excerpt": "We have lots of great updates this release! We&#8217;re super excited to announce this month that both the decomposition tree and drill through button actions are now generally available. On top of this, we have several new features and updates that will really enrich your reporting: curate featured",
      "webUrl": "https://powerbi.microsoft.com/en-us/blog/power-bi-desktop-may-2020-feature-summary/",
      "heat": 97,
      "tags": null,
      "images": [
        {
          "url": "https://powerbi.microsoft.com/pictures/shared/social/social-default-image.png",
          "width": 418,
          "height": 417,
          "title": "Power BI Desktop May 2020 Feature Summary",
          "attribution": null,
          "isCached": true
        }
      ],
      "type": "article",
      "ampWebUrl": null,
      "cdnAmpWebUrl": null,
      "publishedDateTime": "2020-05-19T01:03:56-07:00",
      "updatedDateTime": null,
      "provider": {
        "name": "Microsoft",
        "domain": "microsoft.com",
        "images": [
          {
            "url": "https://smartableai.github.io/microsoft-power-bi/assets/images/organizations/microsoft.com-50x50.jpg",
            "width": 50,
            "height": 50,
            "title": null,
            "attribution": null,
            "isCached": false
          }
        ],
        "publishers": null,
        "authors": null
      },
      "locale": "en-us",
      "categories": [
        "news"
      ],
      "topics": [
        "Power BI"
      ]
    },
    {
      "path": "_news/2020-05-18-lots-of-power-bi-community-posts-roundup-may-18-2020.md",
      "title": "Lots of Power BI community posts... (Roundup | May 18, 2020)",
      "excerpt": "Thanks for watching this week's Power BI news roundup!  Last weeks roundup: https://guyinacu.be/roundup179 2 Minute Tuesday: https://guyinacu.be/copyquery Patrick's tech video: https://guyinacu.be/datepicker Adam's tech video: https://guyinacu.be/matrixkpis  🔴 Live Replay: https://guyinacu.be/35WURjU",
      "webUrl": "https://youtube.com/watch?v=qaZkALLm3hE",
      "heat": 137,
      "tags": null,
      "images": [
        {
          "url": "https://i.ytimg.com/vi/qaZkALLm3hE/maxresdefault.jpg",
          "width": 1280,
          "height": 720,
          "title": "Lots of Power BI community posts... (Roundup | May 18, 2020)",
          "attribution": null,
          "isCached": true
        }
      ],
      "type": "video",
      "ampWebUrl": null,
      "cdnAmpWebUrl": null,
      "publishedDateTime": "2020-05-18T08:00:26-07:00",
      "updatedDateTime": null,
      "provider": {
        "name": "Guy in a Cube",
        "domain": "guyinacube.com",
        "images": [
          {
            "url": "https://smartableai.github.io/microsoft-power-bi/assets/images/organizations/guyinacube.com-50x50.jpg",
            "width": 50,
            "height": 50,
            "title": null,
            "attribution": null,
            "isCached": false
          }
        ],
        "publishers": null,
        "authors": null
      },
      "locale": "en-us",
      "categories": [
        "news"
      ],
      "topics": [
        "Power BI"
      ]
    },
    {
      "path": "_news/2020-05-11-power-bi-announcements-and-a-new-desktop-release-may-11-2020.md",
      "title": "Power BI announcements and a new Desktop release... (May 11, 2020)",
      "excerpt": "Thanks for watching this week's Power BI news roundup!  Last weeks roundup: https://guyinacu.be/roundup178  🔴 MBAS Recap Live Stream Replay: https://guyinacu.be/mbas2020recap  📢 Become a member: https://guyinacu.be/membership   *******************  Want to take your Power BI skills to the next level?",
      "webUrl": "https://youtube.com/watch?v=RqUc3d-0WXY",
      "heat": 137,
      "tags": null,
      "images": [
        {
          "url": "https://i.ytimg.com/vi/RqUc3d-0WXY/maxresdefault.jpg",
          "width": 1280,
          "height": 720,
          "title": "Power BI announcements and a new Desktop release... (May 11, 2020)",
          "attribution": null,
          "isCached": true
        }
      ],
      "type": "video",
      "ampWebUrl": null,
      "cdnAmpWebUrl": null,
      "publishedDateTime": "2020-05-11T08:00:15-07:00",
      "updatedDateTime": null,
      "provider": {
        "name": "Guy in a Cube",
        "domain": "guyinacube.com",
        "images": [
          {
            "url": "https://smartableai.github.io/microsoft-power-bi/assets/images/organizations/guyinacube.com-50x50.jpg",
            "width": 50,
            "height": 50,
            "title": null,
            "attribution": null,
            "isCached": false
          }
        ],
        "publishers": null,
        "authors": null
      },
      "locale": "en-us",
      "categories": [
        "news"
      ],
      "topics": [
        "Power BI"
      ]
    },
    {
      "path": "_news/2020-05-06-power-bi-desktop-update-april-2020.md",
      "title": "Power BI Desktop Update - April 2020",
      "excerpt": "We have a ton of great updates this release! We’re excited to announce a new visual personalization feature to allow your end-users to explore and personalize visuals all within the consumption view of a report! Also this month, if you’re interested in fast refresh scenarios, you will find these new",
      "webUrl": "https://youtube.com/watch?v=q2Hfn_Rhb3E",
      "heat": 154,
      "tags": null,
      "images": [
        {
          "url": "https://i.ytimg.com/vi/q2Hfn_Rhb3E/maxresdefault.jpg",
          "width": 1280,
          "height": 720,
          "title": "Power BI Desktop Update - April 2020",
          "attribution": null,
          "isCached": true
        }
      ],
      "type": "video",
      "ampWebUrl": null,
      "cdnAmpWebUrl": null,
      "publishedDateTime": "2020-05-06T10:18:39-07:00",
      "updatedDateTime": null,
      "provider": {
        "name": "Microsoft",
        "domain": "microsoft.com",
        "images": [
          {
            "url": "https://smartableai.github.io/microsoft-power-bi/assets/images/organizations/microsoft.com-50x50.jpg",
            "width": 50,
            "height": 50,
            "title": null,
            "attribution": null,
            "isCached": false
          }
        ],
        "publishers": null,
        "authors": null
      },
      "locale": "en-us",
      "categories": [
        "news"
      ],
      "topics": [
        "Power BI",
        "Power BI Desktop"
      ]
    }
  ],
  "nextPage": 2
}